[
    {
        "name": "Appium",
        "logo": "https://applitools.com/wp-content/uploads/2020/08/Appium_Hex-1.svg",
        "shortDescription": "this is short",
        "longDescription": "this is slightly longer",
        "frameworkType" : "web",
        "href" : "/quickstart/mobile/appium"
    },
    {
        "name": "Espresso",
        "logo": "https://applitools.com/wp-content/uploads/2020/08/Espresso_Hex-1.svg",
        "href" : "/quickstart/mobile/espresso"
    },
    {
        "name": "Calabash",
        "logo": "https://avatars0.githubusercontent.com/u/66567938?v=4",
        "href" : "/quickstart/mobile/cypress"
    },
    {
        "name": "XCUI",
        "logo": "https://applitools.com/wp-content/uploads/2022/08/xcui-test.png",
        "href" : "/quickstart/mobile/cypress"
    }
]